dataclass_applicative/__init__.py
dataclass_applicative-0.1.0.dist-info/LICENSE
dataclass_applicative-0.1.0.dist-info/WHEEL
dataclass_applicative-0.1.0.dist-info/METADATA
dataclass_applicative-0.1.0.dist-info/RECORD
