Metadata-Version: 2.1
Name: dataclass-applicative
Version: 0.1.0
Summary: 
Home-page: https://github.com/prsteele/dataclass-applicative
License: MIT
Author: Patrick Steele
Author-email: steele.pat@gmail.com
Maintainer: Patrick Steele
Maintainer-email: steele.pat@gmail.com
Requires-Python: >=3.7,<4.0
Classifier: License :: OSI Approved :: MIT License
Classifier: Programming Language :: Python :: 3
Classifier: Programming Language :: Python :: 3.10
Classifier: Programming Language :: Python :: 3.7
Classifier: Programming Language :: Python :: 3.8
Classifier: Programming Language :: Python :: 3.9
Classifier: Topic :: Software Development :: Libraries :: Python Modules
Project-URL: Documentation, https://dataclass-applicative.readthedocs.io/en/latest/
Project-URL: Repository, https://github.com/prsteele/dataclass-applicative
